{
  "_note": "Entry to add to M2_FormulasReference.json in the 'formulas' object (alphabetical order: after 'ButterflyEffect', before 'Capacity')",

  "Calibration": {
    "formula":        "A⊗F⊗It⊗D",
    "formulaASCII":   "A (x) F (x) It (x) D",
    "formulaTeX":     "A \\otimes F \\otimes I_t \\otimes D",
    "dimensions":     4,
    "family":         "Regulatory",
    "perspective":    "territory",
    "contracts":      ["Observable", "Triggerable", "Stateful"],
    "addedInVersion": "15.10.0",
    "notes":          "It = Territory Information (ASFID I, disambiguated vs Im=REVOI Interoperability). A is exogenous/external reference — key distinction from Regulation/Homeostasis where A is endogenous. No Sphinx Eye formula: V⊗O belongs to REVOI poclet scoring, not to the GenericConcept definition."
  }
}
